{
"type": "FeatureCollection",
"name": "Gondomanan_1",
"crs": { "type": "name", "properties": { "name": "urn:ogc:def:crs:OGC:1.3:CRS84" } },
"features": [
{ "type": "Feature", "properties": { "OID_": 0, "Name": "Warni", "FolderPath": "Gondomanan", "SymbolID": 0, "AltMode": -1, "Base": 0.0, "Snippet": null, "PopupInfo": null, "HasLabel": -1, "LabelID": 0 }, "geometry": { "type": "Point", "coordinates": [ 110.372222222000062, -7.805555555999945, 0.0 ] } },
{ "type": "Feature", "properties": { "OID_": 0, "Name": "Agus Riswanto", "FolderPath": "Gondomanan", "SymbolID": 0, "AltMode": -1, "Base": 0.0, "Snippet": null, "PopupInfo": null, "HasLabel": -1, "LabelID": 0 }, "geometry": { "type": "Point", "coordinates": [ 110.370833333000064, -7.805, 0.0 ] } },
{ "type": "Feature", "properties": { "OID_": 0, "Name": "Patningsih Rejeki/Sugeng Widodo", "FolderPath": "Gondomanan/Patningsih Rejeki", "SymbolID": 0, "AltMode": -1, "Base": 0.0, "Snippet": null, "PopupInfo": null, "HasLabel": -1, "LabelID": 0 }, "geometry": { "type": "Point", "coordinates": [ 110.370277778000059, -7.805833332999953, 0.0 ] } },
{ "type": "Feature", "properties": { "OID_": 0, "Name": "Subandrio", "FolderPath": "Gondomanan", "SymbolID": 0, "AltMode": -1, "Base": 0.0, "Snippet": null, "PopupInfo": null, "HasLabel": -1, "LabelID": 0 }, "geometry": { "type": "Point", "coordinates": [ 110.370277778000059, -7.806388888999948, 0.0 ] } }
]
}
