{
"type": "FeatureCollection",
"name": "Mergangsan_1",
"crs": { "type": "name", "properties": { "name": "urn:ogc:def:crs:OGC:1.3:CRS84" } },
"features": [
{ "type": "Feature", "properties": { "OID_": 0, "Name": "Muhammad Sigit", "FolderPath": "Mergangsan", "SymbolID": 0, "AltMode": -1, "Base": 0.0, "Snippet": null, "PopupInfo": null, "HasLabel": -1, "LabelID": 0 }, "geometry": { "type": "Point", "coordinates": [ 110.370392, -7.82193, 0.0 ] } }
]
}
